LICENSE
MANIFEST.in
setup.cfg
setup.py
mintr/__init__.py
mintr.egg-info/PKG-INFO
mintr.egg-info/SOURCES.txt
mintr.egg-info/dependency_links.txt
mintr.egg-info/not-zip-safe
mintr.egg-info/requires.txt
mintr.egg-info/top_level.txt