Metadata-Version: 1.0
Name: mintr
Version: 0.0.8
Summary: An API client for Mint.com
Home-page: https://github.com/shanksauce/mintr
Author: Ben Shank
Author-email: ben@shankware.com
License: MIT
Keywords: client,api,mint,json
Platform: UNKNOWN
